SUILib/__init__.py
SUILib/application.py
SUILib/colors.py
SUILib/graphics.py
SUILib/guielement.py
SUILib/layout.py
SUILib/sound.py
SUILib/splash.py
SUILib/stylemanager.py
SUILib/utils.py
SUILib/assets/icon.png
SUILib/config/styles_dark.json
SUILib/config/styles_light.json
SUILib/elements/__init__.py
SUILib/elements/button.py
SUILib/elements/canvas.py
SUILib/elements/checkbox.py
SUILib/elements/combobox.py
SUILib/elements/graph.py
SUILib/elements/horizontal_scrollbar.py
SUILib/elements/image.py
SUILib/elements/label.py
SUILib/elements/listpanel.py
SUILib/elements/panel.py
SUILib/elements/radiobutton.py
SUILib/elements/slider.py
SUILib/elements/table.py
SUILib/elements/tabpanel.py
SUILib/elements/textinput.py
SUILib/elements/togglebutton.py
SUILib/elements/vertical_scrollbar.py
suilib-0.1.2.dist-info/licenses/LICENSE
suilib-0.1.2.dist-info/METADATA
suilib-0.1.2.dist-info/WHEEL
suilib-0.1.2.dist-info/top_level.txt
suilib-0.1.2.dist-info/RECORD
