Metadata-Version: 2.4
Name: SUILib
Version: 0.1.2
Summary: Simple UI Library for Pygame applications
Author-email: Martin Krcma <martin.krcma1@gmail.com>
License: MIT
Project-URL: Homepage, https://github.com/0xMartin/SUILib
Classifier: Programming Language :: Python :: 3
Classifier: License :: OSI Approved :: MIT License
Classifier: Operating System :: OS Independent
Requires-Python: >=3.7
License-File: LICENSE
Requires-Dist: pygame
Requires-Dist: matplotlib
Requires-Dist: numpy
Dynamic: license-file
